README.md
setup.py
http_checks.egg-info/PKG-INFO
http_checks.egg-info/SOURCES.txt
http_checks.egg-info/dependency_links.txt
http_checks.egg-info/entry_points.txt
http_checks.egg-info/not-zip-safe
http_checks.egg-info/requires.txt
http_checks.egg-info/top_level.txt
httpchecks/__init__.py
httpchecks/httpcheck.py