Metadata-Version: 1.0
Name: http-checks
Version: 0.2.1
Summary: http-checks is an application that can test a couple of hundred urls in seconds
Home-page: https://github.com/Hipo/http-checks
Author: ybrs
Author-email: UNKNOWN
License: UNKNOWN
Platform: UNKNOWN
